concierge/__init__.py
concierge/notifications.py
concierge/templater.py
concierge/utils.py
concierge/core/__init__.py
concierge/core/exceptions.py
concierge/core/lexer.py
concierge/core/parser.py
concierge/core/processor.py
concierge/endpoints/__init__.py
concierge/endpoints/check.py
concierge/endpoints/cli.py
concierge/endpoints/common.py
concierge/endpoints/daemon.py
concierge/endpoints/templates.py
concierge-0.2.2.dist-info/DESCRIPTION.rst
concierge-0.2.2.dist-info/METADATA
concierge-0.2.2.dist-info/RECORD
concierge-0.2.2.dist-info/WHEEL
concierge-0.2.2.dist-info/entry_points.txt
concierge-0.2.2.dist-info/metadata.json
concierge-0.2.2.dist-info/top_level.txt
