Metadata-Version: 2.0
Name: concierge
Version: 0.2.2
Summary: Maintainable SSH config
Home-page: https://github.com/9seconds/concierge
Author: Sergey Arkhipov
Author-email: serge@aerialsounds.org
License: MIT
Platform: UNKNOWN
Classifier: Intended Audience :: Information Technology
Classifier: Intended Audience :: System Administrators
Classifier: Operating System :: POSIX :: Linux
Classifier: Programming Language :: Python
Classifier: Programming Language :: Python :: 3
Classifier: Programming Language :: Python :: 3.3
Classifier: Programming Language :: Python :: 3.4
Classifier: Programming Language :: Python :: 3.5
Requires-Dist: enum34
Requires-Dist: inotify-simple
